apb_slave.sv
module apb_slave (
    input  logic        PCLK,
    input  logic        PRESETn,
    input  logic        PSEL,
    input  logic        PENABLE,
    input  logic        PWRITE,
    input  logic [31:0] PADDR,
    input  logic [31:0] PWDATA,
    output logic [31:0] PRDATA,
    output logic        PREADY,
    output logic        PSLVERR
);

    localparam int MAX_WAIT_CYCLES = 5;  // Maximum wait cycles (0-5 inclusive)
    localparam int WAIT_CNT_W  = $clog2(MAX_WAIT_CYCLES + 1);

    logic [WAIT_CNT_W-1:0] wait_cnt;
    logic [WAIT_CNT_W-1:0] wait_target;
    
    logic [31:0] addr_latched;
    logic [31:0] regfile [0:3];
    logic        xfer_done_next;
    logic        xfer_active;
    logic        pslverr_next;


    
    // Detect when transfer will complete NEXT cycle
    assign xfer_done_next = (PSEL && PENABLE && (wait_cnt == wait_target));

    // ===================================================
    // APB PROTOCOL ASSERTIONS
    // ===================================================
    
    // APB Rule: PREADY can only be high during ACCESS phase
    property p_pready_only_in_access;
        @(posedge PCLK) disable iff (!PRESETn)
        PREADY |-> (PSEL && PENABLE);
    endproperty
    assert_pready_only_in_access: assert property (p_pready_only_in_access)
        else $error("[APB-ASSERT] PREADY asserted outside ACCESS phase");
    
    // APB Rule: Address must be stable during ACCESS phase
    property p_paddr_stable_during_access;
        @(posedge PCLK) disable iff (!PRESETn)
        (PSEL && PENABLE) |-> $stable(PADDR);
    endproperty

    // APB Rule: PENABLE must not assert without PSEL
    property p_penable_requires_psel;
        @(posedge PCLK) disable iff (!PRESETn)
        PENABLE |-> PSEL;
    endproperty
    assert_penable_requires_psel: assert property (p_penable_requires_psel)
        else $error("[APB-ASSERT] PENABLE asserted without PSEL");
    
    // APB Rule: Write/Read only on transfer completion
    property p_write_only_on_completion;
        @(posedge PCLK) disable iff (!PRESETn)
        (xfer_done_next && PWRITE) |-> (PSEL && PENABLE);
    endproperty
    assert_write_only_on_completion: assert property (p_write_only_on_completion)
        else $error("[APB-ASSERT] Write attempted without valid transfer");
    
    property p_read_only_on_completion;
        @(posedge PCLK) disable iff (!PRESETn)
        (xfer_done_next && !PWRITE) |-> (PSEL && PENABLE);
    endproperty
    assert_read_only_on_completion: assert property (p_read_only_on_completion)
        else $error("[APB-ASSERT] Read attempted without valid transfer");
    
    // APB Rule: PSEL should not change during ACCESS phase
    property p_psel_stable_during_access;
        @(posedge PCLK) disable iff (!PRESETn)
        (PSEL && PENABLE) |-> $stable(PSEL);
    endproperty
    assert_psel_stable_during_access: assert property (p_psel_stable_during_access)
        else $error("[APB-ASSERT] PSEL changed during ACCESS phase");
    
    // APB Rule: PWRITE should be stable from SETUP phase until transfer ends
    property p_pwrite_stable_during_transfer;
        @(posedge PCLK) disable iff (!PRESETn)
        (PSEL && PENABLE) |-> $stable(PWRITE);
    endproperty

    assert_pwrite_stable_during_transfer:
        assert property (p_pwrite_stable_during_transfer)
        else $error("[APB-ASSERT] PWRITE changed during ACCESS phase");

    
    // Internal Design Assertions
    property p_xfer_active_implies_psel;
        @(posedge PCLK) disable iff (!PRESETn)
        xfer_active |-> PSEL;
    endproperty
    assert_xfer_active_implies_psel: assert property (p_xfer_active_implies_psel)
        else $error("[DESIGN-ASSERT] xfer_active high without PSEL");
    
    property p_wait_target_range;
        @(posedge PCLK) disable iff (!PRESETn)
        (PSEL && !PENABLE) |-> (wait_target <= WAIT_CNT_W'(MAX_WAIT_CYCLES));
    endproperty
    assert_wait_target_range: assert property (p_wait_target_range)
        else $error("[DESIGN-ASSERT] wait_target exceeds MAX_WAIT_CYCLES");
    
    property p_pready_one_cycle_pulse;
        @(posedge PCLK) disable iff (!PRESETn)
        PREADY |=> !PREADY;
    endproperty
    assert_pready_one_cycle_pulse: assert property (p_pready_one_cycle_pulse)
        else $error("[DESIGN-ASSERT] PREADY asserted for more than 1 cycle");
    
    
    
    // ===================================================
    // PREADY and wait counter logic
    // ===================================================
    always_ff @(posedge PCLK or negedge PRESETn) begin
        if (!PRESETn) begin
            wait_cnt    <= '0;
            wait_target <= '0;
            PREADY      <= 1'b0;
            xfer_active <= 1'b0;
        end
        // NEW TRANSFER → RESET WAIT
        else if (PSEL && !PENABLE) begin
            wait_cnt    <= '0;
            PREADY      <= 1'b0;
            xfer_active <= 1'b1;
            
            // Random wait cycles 1-5
            begin
                logic [31:0] rand_val;
                rand_val = $urandom;
                wait_target <= WAIT_CNT_W'((rand_val % 6));  // 1-5
            end
        end
        // ACCESS PHASE → COUNT
        else if (PSEL && PENABLE && xfer_active) begin
            if (wait_cnt == wait_target) begin
                PREADY      <= 1'b1;
                xfer_active <= 1'b0;
                wait_cnt    <= wait_cnt;
            end else begin
                wait_cnt <= wait_cnt + 1'b1;
                PREADY   <= 1'b0;
            end
        end
        // Idle or transfer ended
        else begin
            PREADY <= 1'b0;
            if (!PSEL) begin
                xfer_active <= 1'b0;
                wait_cnt    <= '0;
            end
        end
    end

    // ===================================================
    // ADDRESS LATCH
    // ===================================================
    always_ff @(posedge PCLK or negedge PRESETn) begin
        if (!PRESETn) begin
            addr_latched <= 32'b0;
        end
        // latch on every SETUP phase
        else if (PSEL && !PENABLE) begin
            addr_latched <= PADDR;
        end
    end

    // ===================================================
    // PSLVERR Logic
    // ===================================================
    always_comb begin
        pslverr_next = 1'b0;
        
        // Set PSLVERR for invalid addresses on transfer completion
        if (xfer_done_next) begin
            case (addr_latched)
                32'h1000, 32'h1004, 32'h1008, 32'h100C: begin
                    // Valid addresses - no error
                    pslverr_next = 1'b0;
                end
                default: begin
                    // Invalid address - set error
                    pslverr_next = 1'b1;
                end
            endcase
        end
    end

    always_ff @(posedge PCLK or negedge PRESETn) begin
        if (!PRESETn) begin
            PSLVERR <= 1'b0;
        end else begin
            PSLVERR <= pslverr_next;
        end
    end

    // PSLVERR Assertions
    property p_pslverr_only_on_completion;
        @(posedge PCLK) disable iff (!PRESETn)
        $rose(PSLVERR) |-> $past(xfer_done_next);
    endproperty

    assert_pslverr_only_on_completion:
        assert property (p_pslverr_only_on_completion)
        else $error("[PSLVERR-ASSERT] PSLVERR asserted without transfer completion");




    property p_pslverr_for_invalid_addr;
        @(posedge PCLK) disable iff (!PRESETn)
        (xfer_done_next && !(addr_latched inside {32'h1000, 32'h1004, 32'h1008, 32'h100C})) |=> PSLVERR;
    endproperty
    assert_pslverr_for_invalid_addr: assert property (p_pslverr_for_invalid_addr)
        else $error("[PSLVERR-ASSERT] Invalid address didn't generate PSLVERR");

    // ===================================================
    // WRITE
    // ===================================================
    always_ff @(posedge PCLK or negedge PRESETn) begin
        if (!PRESETn) begin
            regfile[0] <= 32'b0;
            regfile[1] <= 32'b0;
            regfile[2] <= 32'b0;
            regfile[3] <= 32'b0;
        end
        // Write happens when transfer WILL complete next cycle
        else if (xfer_done_next && PWRITE) begin
            case (addr_latched)
                32'h1000: regfile[0] <= PWDATA;
                32'h1004: regfile[1] <= PWDATA;
                32'h1008: regfile[2] <= PWDATA;
                32'h100C: regfile[3] <= PWDATA;
                default: begin
                    // Invalid address - no write (PSLVERR already set)
                end
            endcase
        end
    end

    // ===================================================
    // READ
    // ===================================================
    always_ff @(posedge PCLK or negedge PRESETn) begin
        if (!PRESETn) begin
            PRDATA <= 32'b0;
        end
        // Update PRDATA when transfer WILL complete next cycle
        else if (xfer_done_next && !PWRITE) begin
            case (addr_latched)
                32'h1000: PRDATA <= regfile[0];
                32'h1004: PRDATA <= regfile[1];
                32'h1008: PRDATA <= regfile[2];
                32'h100C: PRDATA <= regfile[3];
                default:  PRDATA <= 32'b0;
            endcase
        end
        // Clear PRDATA when no transfer is active
        else if (!PSEL) begin
            PRDATA <= 32'b0;
        end
    end

endmodule

tb.sv
`timescale 1ns/1ps

module tb;
    logic PCLK;
    logic PRESETn;
    logic PSEL;
    logic PENABLE;
    logic PWRITE;
    logic [31:0] PADDR;
    logic [31:0] PWDATA;
    logic [31:0] PRDATA;
    logic PREADY;
    logic PSLVERR;

    // Clock generation
    initial begin
        PCLK = 0;
        forever #5 PCLK = ~PCLK;  // 10ns period = 100MHz
    end

    // Instantiate DUT
    apb_slave dut (
        .PCLK(PCLK),
        .PRESETn(PRESETn),
        .PSEL(PSEL),
        .PENABLE(PENABLE),
        .PWRITE(PWRITE),
        .PADDR(PADDR),
        .PWDATA(PWDATA),
        .PRDATA(PRDATA),
        .PREADY(PREADY),
        .PSLVERR(PSLVERR)
    );

    // VCD dump for debugging
    initial begin
        $dumpfile("apb_wave.vcd");
        $dumpvars(0, tb);
    end

    // Monitor for assertions (prints when assertions fire)
    initial begin
        $display("[TB] Starting APB slave testbench");
    end

    // End simulation after timeout
    initial begin
        #1000000;  // 1ms timeout
        $display("[TB] Simulation timeout");
        $finish;
    end
endmodule

apb_wave.vcd
$version Generated by VerilatedVcd $end
$timescale 1ps $end
 $scope module tb $end
  $var wire 1 # PCLK $end
  $var wire 1 $ PRESETn $end
  $var wire 1 % PSEL $end
  $var wire 1 & PENABLE $end
  $var wire 1 ' PWRITE $end
  $var wire 32 ( PADDR [31:0] $end
  $var wire 32 ) PWDATA [31:0] $end
  $var wire 32 * PRDATA [31:0] $end
  $var wire 1 + PREADY $end
  $var wire 1 , PSLVERR $end
  $scope module dut $end
   $var wire 1 - PCLK $end
   $var wire 1 . PRESETn $end
   $var wire 1 / PSEL $end
   $var wire 1 0 PENABLE $end
   $var wire 1 1 PWRITE $end
   $var wire 32 2 PADDR [31:0] $end
   $var wire 32 3 PWDATA [31:0] $end
   $var wire 32 4 PRDATA [31:0] $end
   $var wire 1 5 PREADY $end
   $var wire 1 6 PSLVERR $end
   $var wire 32 B MAX_WAIT_CYCLES [31:0] $end
   $var wire 32 C WAIT_CNT_W [31:0] $end
   $var wire 3 7 wait_cnt [2:0] $end
   $var wire 3 8 wait_target [2:0] $end
   $var wire 32 9 addr_latched [31:0] $end
   $var wire 32 : regfile[0] [31:0] $end
   $var wire 32 ; regfile[1] [31:0] $end
   $var wire 32 < regfile[2] [31:0] $end
   $var wire 32 = regfile[3] [31:0] $end
   $var wire 1 > xfer_done_next $end
   $var wire 1 ? xfer_active $end
   $var wire 1 @ pslverr_next $end
   $scope module unnamedblk1 $end
    $var wire 32 A rand_val [31:0] $end
   $upscope $end
  $upscope $end
 $upscope $end
$enddefinitions $end


#0
0#
0$
0%
0&
0'
b00000000000000000000000000000000 (
b00000000000000000000000000000000 )
b00000000000000000000000000000000 *
0+
0,
0-
0.
0/
00
01
b00000000000000000000000000000000 2
b00000000000000000000000000000000 3
b00000000000000000000000000000000 4
05
06
b000 7
b000 8
b00000000000000000000000000000000 9
b00000000000000000000000000000000 :
b00000000000000000000000000000000 ;
b00000000000000000000000000000000 <
b00000000000000000000000000000000 =
0>
0?
0@
b00000000000000000000000000000000 A
b00000000000000000000000000000101 B
b00000000000000000000000000000011 C
#5000
1#
1-
#10000
0#
0-
#15000
1#
1-
#20000
0#
1$
0-
1.
#25000
1#
1-
#30000
0#
0-
#35000
1#
1%
1'
b00000000000000000001000000000000 (
b10100101101001011010010110100101 )
1-
1/
11
b00000000000000000001000000000000 2
b10100101101001011010010110100101 3
#40000
0#
0-
#45000
1#
1&
1-
10
b100 8
b00000000000000000001000000000000 9
1?
b01111001011101100111001111000100 A
#50000
0#
0-
#55000
1#
1-
b001 7
#60000
0#
0-
#65000
1#
1-
b010 7
#70000
0#
0-
#75000
1#
1-
b011 7
#80000
0#
0-
#85000
1#
1-
b100 7
1>
#90000
0#
0-
#95000
1#
1+
1-
15
b10100101101001011010010110100101 :
0?
#100000
0#
0-
#105000
1#
0%
0&
0'
b00000000000000000000000000000000 (
b00000000000000000000000000000000 )
0+
1-
0/
00
01
b00000000000000000000000000000000 2
b00000000000000000000000000000000 3
05
0>
#110000
0#
0-
#115000
1#
1-
b000 7
#120000
0#
0-
#125000
1#
1%
1'
b00000000000000000001000000000100 (
b01010101010101010101010101010101 )
1-
1/
11
b00000000000000000001000000000100 2
b01010101010101010101010101010101 3
#130000
0#
0-
#135000
1#
1&
1-
10
b010 8
b00000000000000000001000000000100 9
1?
b00001011000111100101110110011100 A
#140000
0#
0-
#145000
1#
1-
b001 7
#150000
0#
0-
#155000
1#
1-
b010 7
1>
#160000
0#
0-
#165000
1#
1+
1-
15
b01010101010101010101010101010101 ;
0?
#170000
0#
0-
#175000
1#
0%
0&
0'
b00000000000000000000000000000000 (
b00000000000000000000000000000000 )
0+
1-
0/
00
01
b00000000000000000000000000000000 2
b00000000000000000000000000000000 3
05
0>
#180000
0#
0-
#185000
1#
1-
b000 7
#190000
0#
0-
#195000
1#
1%
1'
b00000000000000000001000000001000 (
b00010010001101000101011001111000 )
1-
1/
11
b00000000000000000001000000001000 2
b00010010001101000101011001111000 3
#200000
0#
0-
#205000
1#
1&
1-
10
b00000000000000000001000000001000 9
1?
b10011110111111011101010100000010 A
#210000
0#
0-
#215000
1#
1-
b001 7
#220000
0#
0-
#225000
1#
1-
b010 7
1>
#230000
0#
0-
#235000
1#
1+
1-
15
b00010010001101000101011001111000 <
0?
#240000
0#
0-
#245000
1#
0%
0&
0'
b00000000000000000000000000000000 (
b00000000000000000000000000000000 )
0+
1-
0/
00
01
b00000000000000000000000000000000 2
b00000000000000000000000000000000 3
05
0>
#250000
0#
0-
#255000
1#
1-
b000 7
#260000
0#
0-
#265000
1#
1%
1'
b00000000000000000001000000001100 (
b10000111011001010100001100100001 )
1-
1/
11
b00000000000000000001000000001100 2
b10000111011001010100001100100001 3
#270000
0#
0-
#275000
1#
1&
1-
10
b100 8
b00000000000000000001000000001100 9
1?
b01001000110000101110000011100100 A
#280000
0#
0-
#285000
1#
1-
b001 7
#290000
0#
0-
#295000
1#
1-
b010 7
#300000
0#
0-
#305000
1#
1-
b011 7
#310000
0#
0-
#315000
1#
1-
b100 7
1>
#320000
0#
0-
#325000
1#
1+
1-
15
b10000111011001010100001100100001 =
0?
#330000
0#
0-
#335000
1#
0%
0&
0'
b00000000000000000000000000000000 (
b00000000000000000000000000000000 )
0+
1-
0/
00
01
b00000000000000000000000000000000 2
b00000000000000000000000000000000 3
05
0>
#340000
0#
0-
#345000
1#
1%
b00000000000000000001000000000000 (
1-
1/
b00000000000000000001000000000000 2
b000 7
#350000
0#
0-
#355000
1#
1&
1-
10
b000 8
b00000000000000000001000000000000 9
1>
1?
b10010010000101111000001101111000 A
#360000
0#
0-
#365000
1#
b10100101101001011010010110100101 *
1+
1-
b10100101101001011010010110100101 4
15
0?
#370000
0#
0-
#375000
1#
0%
0&
b00000000000000000000000000000000 (
0+
1-
0/
00
b00000000000000000000000000000000 2
05
0>
#380000
0#
0-
#385000
1#
1%
b00000000000000000001000000000100 (
b00000000000000000000000000000000 *
1-
1/
b00000000000000000001000000000100 2
b00000000000000000000000000000000 4
#390000
0#
0-
#395000
1#
1&
1-
10
b100 8
b00000000000000000001000000000100 9
1?
b10111011110101011000111010111100 A
#400000
0#
0-
#405000
1#
1-
b001 7
#410000
0#
0-
#415000
1#
1-
b010 7
#420000
0#
0-
#425000
1#
1-
b011 7
#430000
0#
0-
#435000
1#
1-
b100 7
1>
#440000
0#
0-
#445000
1#
b01010101010101010101010101010101 *
1+
1-
b01010101010101010101010101010101 4
15
0?
#450000
0#
0-
#455000
1#
0%
0&
b00000000000000000000000000000000 (
0+
1-
0/
00
b00000000000000000000000000000000 2
05
0>
#460000
0#
0-
#465000
1#
1%
b00000000000000000001000000001000 (
b00000000000000000000000000000000 *
1-
1/
b00000000000000000001000000001000 2
b00000000000000000000000000000000 4
b000 7
#470000
0#
0-
#475000
1#
1&
1-
10
b00000000000000000001000000001000 9
1?
b11001010101001001001111010110110 A
#480000
0#
0-
#485000
1#
1-
b001 7
#490000
0#
0-
#495000
1#
1-
b010 7
#500000
0#
0-
#505000
1#
1-
b011 7
#510000
0#
0-
#515000
1#
1-
b100 7
1>
#520000
0#
0-
#525000
1#
b00010010001101000101011001111000 *
1+
1-
b00010010001101000101011001111000 4
15
0?
#530000
0#
0-
#535000
1#
0%
0&
b00000000000000000000000000000000 (
0+
1-
0/
00
b00000000000000000000000000000000 2
05
0>
#540000
0#
0-
#545000
1#
1%
b00000000000000000001000000001100 (
b00000000000000000000000000000000 *
1-
1/
b00000000000000000001000000001100 2
b00000000000000000000000000000000 4
b000 7
#550000
0#
0-
#555000
1#
1&
1-
10
b010 8
b00000000000000000001000000001100 9
1?
b00101010000101001111111111100100 A
#560000
0#
0-
#565000
1#
1-
b001 7
#570000
0#
0-
#575000
1#
1-
b010 7
1>
#580000
0#
0-
#585000
1#
b10000111011001010100001100100001 *
1+
1-
b10000111011001010100001100100001 4
15
0?
#590000
0#
0-
#595000
1#
0%
0&
b00000000000000000000000000000000 (
0+
1-
0/
00
b00000000000000000000000000000000 2
05
0>
#600000
0#
0-
#605000
1#
b00000000000000000000000000000000 *
1-
b00000000000000000000000000000000 4
b000 7
#610000
0#
0-
#615000
1#
1%
1'
b00000000000000000001000000000000 (
b11011110101011011011111011101111 )
1-
1/
11
b00000000000000000001000000000000 2
b11011110101011011011111011101111 3
#620000
0#
0-
#625000
1#
1&
1-
10
b101 8
b00000000000000000001000000000000 9
1?
b01111101011011111111001110110111 A
#630000
0#
0-
#635000
1#
1-
b001 7
#640000
0#
0-
#645000
1#
1-
b010 7
#650000
0#
0-
#655000
1#
1-
b011 7
#660000
0#
0-
#665000
1#
1-
b100 7
#670000
0#
0-
#675000
1#
1-
b101 7
1>
#680000
0#
0-
#685000
1#
1+
1-
15
b11011110101011011011111011101111 :
0?
#690000
0#
0-
#695000
1#
0%
0&
0'
b00000000000000000000000000000000 (
b00000000000000000000000000000000 )
0+
1-
0/
00
01
b00000000000000000000000000000000 2
b00000000000000000000000000000000 3
05
0>
#700000
0#
0-
#705000
1#
1%
b00000000000000000001000000000000 (
1-
1/
b00000000000000000001000000000000 2
b000 7
#710000
0#
0-
#715000
1#
1&
1-
10
1?
b11111100110001000111000101010011 A
#720000
0#
0-
#725000
1#
1-
b001 7
#730000
0#
0-
#735000
1#
1-
b010 7
#740000
0#
0-
#745000
1#
1-
b011 7
#750000
0#
0-
#755000
1#
1-
b100 7
#760000
0#
0-
#765000
1#
1-
b101 7
1>
#770000
0#
0-
#775000
1#
b11011110101011011011111011101111 *
1+
1-
b11011110101011011011111011101111 4
15
0?
#780000
0#
0-
#785000
1#
0%
0&
b00000000000000000000000000000000 (
0+
1-
0/
00
b00000000000000000000000000000000 2
05
0>
#790000
0#
0-
#795000
1#
b00000000000000000000000000000000 *
1-
b00000000000000000000000000000000 4
b000 7
#800000
0#
0-
#805000
1#
1%
1'
b00000000000000000001000000000100 (
b11001010111111101011101010111110 )
1-
1/
11
b00000000000000000001000000000100 2
b11001010111111101011101010111110 3
#810000
0#
0-
#815000
1#
1&
1-
10
b001 8
b00000000000000000001000000000100 9
1?
b01101111100111100001011100100001 A
#820000
0#
0-
#825000
1#
1-
b001 7
1>
#830000
0#
0-
#835000
1#
1+
1-
15
b11001010111111101011101010111110 ;
0?
#840000
0#
0-
#845000
1#
0%
0&
0'
b00000000000000000000000000000000 (
b00000000000000000000000000000000 )
0+
1-
0/
00
01
b00000000000000000000000000000000 2
b00000000000000000000000000000000 3
05
0>
#850000
0#
0-
#855000
1#
1%
b00000000000000000001000000000100 (
1-
1/
b00000000000000000001000000000100 2
b000 7
#860000
0#
0-
#865000
1#
1&
1-
10
b011 8
1?
b10001010100110100111110111100001 A
#870000
0#
0-
#875000
1#
1-
b001 7
#880000
0#
0-
#885000
1#
1-
b010 7
#890000
0#
0-
#895000
1#
1-
b011 7
1>
#900000
0#
0-
#905000
1#
b11001010111111101011101010111110 *
1+
1-
b11001010111111101011101010111110 4
15
0?
#910000
0#
0-
#915000
1#
0%
0&
b00000000000000000000000000000000 (
0+
1-
0/
00
b00000000000000000000000000000000 2
05
0>
#920000
0#
0-
#925000
1#
b00000000000000000000000000000000 *
1-
b00000000000000000000000000000000 4
b000 7
#930000
0#
0-
#935000
1#
1%
1'
b00000000000000000001000000001000 (
b11110000000011011111000000001101 )
1-
1/
11
b00000000000000000001000000001000 2
b11110000000011011111000000001101 3
#940000
0#
0-
#945000
1#
1&
1-
10
b00000000000000000001000000001000 9
1?
b11011111100011001010111111000101 A
#950000
0#
0-
#955000
1#
1-
b001 7
#960000
0#
0-
#965000
1#
1-
b010 7
#970000
0#
0-
#975000
1#
1-
b011 7
1>
#980000
0#
0-
#985000
1#
1+
1-
15
b11110000000011011111000000001101 <
0?
#990000
0#
0-
#995000
1#
0%
0&
0'
b00000000000000000000000000000000 (
b00000000000000000000000000000000 )
0+
1-
0/
00
01
b00000000000000000000000000000000 2
b00000000000000000000000000000000 3
05
0>
#1000000
0#
0-
#1005000
1#
1%
b00000000000000000001000000001000 (
1-
1/
b00000000000000000001000000001000 2
b000 7
#1010000
0#
0-
#1015000
1#
1&
1-
10
b000 8
1>
1?
b00010010010100111111001110000010 A
#1020000
0#
0-
#1025000
1#
b11110000000011011111000000001101 *
1+
1-
b11110000000011011111000000001101 4
15
0?
#1030000
0#
0-
#1035000
1#
0%
0&
b00000000000000000000000000000000 (
0+
1-
0/
00
b00000000000000000000000000000000 2
05
0>
#1040000
0#
0-
#1045000
1#
b00000000000000000000000000000000 *
1-
b00000000000000000000000000000000 4
#1050000
0#
0-
#1055000
1#
1%
1'
b00000000000000000001000000001100 (
b10111010101011011111000000001101 )
1-
1/
11
b00000000000000000001000000001100 2
b10111010101011011111000000001101 3
#1060000
0#
0-
#1065000
1#
1&
1-
10
b100 8
b00000000000000000001000000001100 9
1?
b10100100010100011111111101100010 A
#1070000
0#
0-
#1075000
1#
1-
b001 7
#1080000
0#
0-
#1085000
1#
1-
b010 7
#1090000
0#
0-
#1095000
1#
1-
b011 7
#1100000
0#
0-
#1105000
1#
1-
b100 7
1>
#1110000
0#
0-
#1115000
1#
1+
1-
15
b10111010101011011111000000001101 =
0?
#1120000
0#
0-
#1125000
1#
0%
0&
0'
b00000000000000000000000000000000 (
b00000000000000000000000000000000 )
0+
1-
0/
00
01
b00000000000000000000000000000000 2
b00000000000000000000000000000000 3
05
0>
#1130000
0#
0-
#1135000
1#
1%
b00000000000000000001000000001100 (
1-
1/
b00000000000000000001000000001100 2
b000 7
#1140000
0#
0-
#1145000
1#
1&
1-
10
b101 8
1?
b01110011010110000001011000110101 A
#1150000
0#
0-
#1155000
1#
1-
b001 7
#1160000
0#
0-
#1165000
1#
1-
b010 7
#1170000
0#
0-
#1175000
1#
1-
b011 7
#1180000
0#
0-
#1185000
1#
1-
b100 7
#1190000
0#
0-
#1195000
1#
1-
b101 7
1>
#1200000
0#
0-
#1205000
1#
b10111010101011011111000000001101 *
1+
1-
b10111010101011011111000000001101 4
15
0?
#1210000
0#
0-
#1215000
1#
0%
0&
b00000000000000000000000000000000 (
0+
1-
0/
00
b00000000000000000000000000000000 2
05
0>
#1220000
0#
0-
#1225000
1#
b00000000000000000000000000000000 *
1-
b00000000000000000000000000000000 4
b000 7
#1230000
0#
0-
#1235000
1#
1%
1'
b00000000000000000001000000000000 (
b00010001000100010001000100010001 )
1-
1/
11
b00000000000000000001000000000000 2
b00010001000100010001000100010001 3
#1240000
0#
0-
#1245000
1#
1&
1-
10
b100 8
b00000000000000000001000000000000 9
1?
b10101101111110111100100100010010 A
#1250000
0#
0-
#1255000
1#
1-
b001 7
#1260000
0#
0-
#1265000
1#
1-
b010 7
#1270000
0#
0-
#1275000
1#
1-
b011 7
#1280000
0#
0-
#1285000
1#
1-
b100 7
1>
#1290000
0#
0-
#1295000
1#
1+
1-
15
b00010001000100010001000100010001 :
0?
#1300000
0#
0-
#1305000
1#
0%
0&
0'
b00000000000000000000000000000000 (
b00000000000000000000000000000000 )
0+
1-
0/
00
01
b00000000000000000000000000000000 2
b00000000000000000000000000000000 3
05
0>
#1310000
0#
0-
#1315000
1#
1%
b00000000000000000001000000000000 (
1-
1/
b00000000000000000001000000000000 2
b000 7
#1320000
0#
0-
#1325000
1#
1&
1-
10
1?
b01100010111110011010101101010110 A
#1330000
0#
0-
#1335000
1#
1-
b001 7
#1340000
0#
0-
#1345000
1#
1-
b010 7
#1350000
0#
0-
#1355000
1#
1-
b011 7
#1360000
0#
0-
#1365000
1#
1-
b100 7
1>
#1370000
0#
0-
#1375000
1#
b00010001000100010001000100010001 *
1+
1-
b00010001000100010001000100010001 4
15
0?
#1380000
0#
0-
#1385000
1#
0%
0&
b00000000000000000000000000000000 (
0+
1-
0/
00
b00000000000000000000000000000000 2
05
0>
#1390000
0#
0-
#1395000
1#
b00000000000000000000000000000000 *
1-
b00000000000000000000000000000000 4
b000 7
#1400000
0#
0-
#1405000
1#
1%
1'
b00000000000000000001000000000100 (
b00100010001000100010001000100010 )
1-
1/
11
b00000000000000000001000000000100 2
b00100010001000100010001000100010 3
#1410000
0#
0-
#1415000
1#
1&
1-
10
b101 8
b00000000000000000001000000000100 9
1?
b10110100001100100011101111111101 A
#1420000
0#
0-
#1425000
1#
1-
b001 7
#1430000
0#
0-
#1435000
1#
1-
b010 7
#1440000
0#
0-
#1445000
1#
1-
b011 7
#1450000
0#
0-
#1455000
1#
1-
b100 7
#1460000
0#
0-
#1465000
1#
1-
b101 7
1>
#1470000
0#
0-
#1475000
1#
1+
1-
15
b00100010001000100010001000100010 ;
0?
#1480000
0#
0-
#1485000
1#
0%
0&
0'
b00000000000000000000000000000000 (
b00000000000000000000000000000000 )
0+
1-
0/
00
01
b00000000000000000000000000000000 2
b00000000000000000000000000000000 3
05
0>
#1490000
0#
0-
#1495000
1#
1%
b00000000000000000001000000000100 (
1-
1/
b00000000000000000001000000000100 2
b000 7
#1500000
0#
0-
#1505000
1#
1&
1-
10
b000 8
1>
1?
b11011100011010110100000111110100 A
#1510000
0#
0-
#1515000
1#
b00100010001000100010001000100010 *
1+
1-
b00100010001000100010001000100010 4
15
0?
#1520000
0#
0-
#1525000
1#
0%
0&
b00000000000000000000000000000000 (
0+
1-
0/
00
b00000000000000000000000000000000 2
05
0>
#1530000
0#
0-
#1535000
1#
b00000000000000000000000000000000 *
1-
b00000000000000000000000000000000 4
#1540000
0#
0-
#1545000
1#
1%
1'
b00000000000000000001000000001000 (
b00110011001100110011001100110011 )
1-
1/
11
b00000000000000000001000000001000 2
b00110011001100110011001100110011 3
#1550000
0#
0-
#1555000
1#
1&
1-
10
b011 8
b00000000000000000001000000001000 9
1?
b00000110101011011111010100111011 A
#1560000
0#
0-
#1565000
1#
1-
b001 7
#1570000
0#
0-
#1575000
1#
1-
b010 7
#1580000
0#
0-
#1585000
1#
1-
b011 7
1>
#1590000
0#
0-
#1595000
1#
1+
1-
15
b00110011001100110011001100110011 <
0?
#1600000
0#
0-
#1605000
1#
0%
0&
0'
b00000000000000000000000000000000 (
b00000000000000000000000000000000 )
0+
1-
0/
00
01
b00000000000000000000000000000000 2
b00000000000000000000000000000000 3
05
0>
#1610000
0#
0-
#1615000
1#
1%
b00000000000000000001000000001000 (
1-
1/
b00000000000000000001000000001000 2
b000 7
#1620000
0#
0-
#1625000
1#
1&
1-
10
b100 8
1?
b11000110011011010100110101011000 A
#1630000
0#
0-
#1635000
1#
1-
b001 7
#1640000
0#
0-
#1645000
1#
1-
b010 7
#1650000
0#
0-
#1655000
1#
1-
b011 7
#1660000
0#
0-
#1665000
1#
1-
b100 7
1>
#1670000
0#
0-
#1675000
1#
b00110011001100110011001100110011 *
1+
1-
b00110011001100110011001100110011 4
15
0?
#1680000
0#
0-
#1685000
1#
0%
0&
b00000000000000000000000000000000 (
0+
1-
0/
00
b00000000000000000000000000000000 2
05
0>
#1690000
0#
0-
#1695000
1#
b00000000000000000000000000000000 *
1-
b00000000000000000000000000000000 4
b000 7
#1700000
0#
0-
#1705000
1#
1%
1'
b00000000000000000001000000001100 (
b01000100010001000100010001000100 )
1-
1/
11
b00000000000000000001000000001100 2
b01000100010001000100010001000100 3
#1710000
0#
0-
#1715000
1#
1&
1-
10
b00000000000000000001000000001100 9
1?
b11101001110011110000010010110010 A
#1720000
0#
0-
#1725000
1#
1-
b001 7
#1730000
0#
0-
#1735000
1#
1-
b010 7
#1740000
0#
0-
#1745000
1#
1-
b011 7
#1750000
0#
0-
#1755000
1#
1-
b100 7
1>
#1760000
0#
0-
#1765000
1#
1+
1-
15
b01000100010001000100010001000100 =
0?
#1770000
0#
0-
#1775000
1#
0%
0&
0'
b00000000000000000000000000000000 (
b00000000000000000000000000000000 )
0+
1-
0/
00
01
b00000000000000000000000000000000 2
b00000000000000000000000000000000 3
05
0>
#1780000
0#
0-
#1785000
1#
1%
b00000000000000000001000000001100 (
1-
1/
b00000000000000000001000000001100 2
b000 7
#1790000
0#
0-
#1795000
1#
1&
1-
10
b010 8
1?
b01010110110100010000100001011100 A
#1800000
0#
0-
#1805000
1#
1-
b001 7
#1810000
0#
0-
#1815000
1#
1-
b010 7
1>
#1820000
0#
0-
#1825000
1#
b01000100010001000100010001000100 *
1+
1-
b01000100010001000100010001000100 4
15
0?
#1830000
0#
0-
#1835000
1#
0%
0&
b00000000000000000000000000000000 (
0+
1-
0/
00
b00000000000000000000000000000000 2
05
0>
#1840000
0#
0-
#1845000
1#
b00000000000000000000000000000000 *
1-
b00000000000000000000000000000000 4
b000 7
#1850000
0#
0-
#1855000
1#
1%
1'
b00000000000000000001000000000000 (
b01010101010101010101010101010101 )
1-
1/
11
b00000000000000000001000000000000 2
b01010101010101010101010101010101 3
#1860000
0#
0-
#1865000
1#
1&
1-
10
b100 8
b00000000000000000001000000000000 9
1?
b01011010000110111000010100011110 A
#1870000
0#
0-
#1875000
1#
1-
b001 7
#1880000
0#
0-
#1885000
1#
1-
b010 7
#1890000
0#
0-
#1895000
1#
1-
b011 7
#1900000
0#
0-
#1905000
1#
1-
b100 7
1>
#1910000
0#
0-
