apb_slave.sv
module apb_slave (
    input  logic        PCLK,
    input  logic        PRESETn,
    input  logic        PSEL,
    input  logic        PENABLE,
    input  logic        PWRITE,
    input  logic [31:0] PADDR,
    input  logic [31:0] PWDATA,
    output logic [31:0] PRDATA,
    output logic        PREADY,
    output logic        PSLVERR
);

    // 4 memory mapped registers
    logic [31:0] regfile [0:3];

    // internal
    logic [31:0] addr_latched;

    //---------------------------------
    // Always ready (no wait states for now)
    //---------------------------------
    assign PREADY  = 1'b1;
    assign PSLVERR = 1'b0;

    //---------------------------------
    // Latch address in SETUP phase
    //---------------------------------
    always_ff @(posedge PCLK or negedge PRESETn) begin
        if (!PRESETn)
            addr_latched <= 32'b0;
        else if (PSEL && !PENABLE)
            addr_latched <= PADDR;
    end

    //---------------------------------
    // Write operation
    //---------------------------------
    always_ff @(posedge PCLK or negedge PRESETn) begin
        if (!PRESETn) begin
            regfile[0] <= 32'b0;
            regfile[1] <= 32'b0;
            regfile[2] <= 32'b0;
            regfile[3] <= 32'b0;
        end
        else if (PSEL && PENABLE && PWRITE) begin
            case (addr_latched)
                32'h1000: regfile[0] <= PWDATA;
                32'h1004: regfile[1] <= PWDATA;
                32'h1008: regfile[2] <= PWDATA;
                32'h100C: regfile[3] <= PWDATA;
            endcase
        end
    end

    //---------------------------------
    // Read operation
    //---------------------------------
    always_comb begin
        PRDATA = 32'b0;
        if (PSEL && PENABLE && !PWRITE) begin
            case (addr_latched)
                32'h1000: PRDATA = regfile[0];
                32'h1004: PRDATA = regfile[1];
                32'h1008: PRDATA = regfile[2];
                32'h100C: PRDATA = regfile[3];
            endcase
        end
    end

endmodule

tb.sv
module tb;

    reg PCLK;
    reg PRESETn;

    reg         PSEL;
    reg         PENABLE;
    reg         PWRITE;
    reg  [31:0] PADDR;
    reg  [31:0] PWDATA;
    wire [31:0] PRDATA;
    wire        PREADY;
    wire        PSLVERR;

    // Clock
    initial begin
        PCLK = 0;
        forever #5 PCLK = ~PCLK;
    end



    // DUT
    apb_slave dut (
        .PCLK    (PCLK),
        .PRESETn (PRESETn),
        .PSEL    (PSEL),
        .PENABLE (PENABLE),
        .PWRITE  (PWRITE),
        .PADDR   (PADDR),
        .PWDATA  (PWDATA),
        .PRDATA  (PRDATA),
        .PREADY  (PREADY),
        .PSLVERR (PSLVERR)
    );

endmodule

dump.vcd
$version Generated by VerilatedVcd $end
$timescale 1ps $end
 $scope module tb $end
  $var wire 1 # PCLK $end
  $var wire 1 $ PRESETn $end
  $var wire 1 % PSEL $end
  $var wire 1 & PENABLE $end
  $var wire 1 ' PWRITE $end
  $var wire 32 ( PADDR [31:0] $end
  $var wire 32 ) PWDATA [31:0] $end
  $var wire 32 * PRDATA [31:0] $end
  $var wire 1 + PREADY $end
  $var wire 1 , PSLVERR $end
  $scope module dut $end
   $var wire 1 - PCLK $end
   $var wire 1 . PRESETn $end
   $var wire 1 / PSEL $end
   $var wire 1 0 PENABLE $end
   $var wire 1 1 PWRITE $end
   $var wire 32 2 PADDR [31:0] $end
   $var wire 32 3 PWDATA [31:0] $end
   $var wire 32 4 PRDATA [31:0] $end
   $var wire 1 5 PREADY $end
   $var wire 1 6 PSLVERR $end
   $var wire 32 7 regfile[0] [31:0] $end
   $var wire 32 8 regfile[1] [31:0] $end
   $var wire 32 9 regfile[2] [31:0] $end
   $var wire 32 : regfile[3] [31:0] $end
   $var wire 32 ; addr_latched [31:0] $end
  $upscope $end
 $upscope $end
$enddefinitions $end


#0
0#
0$
0%
0&
0'
b00000000000000000000000000000000 (
b00000000000000000000000000000000 )
b00000000000000000000000000000000 *
1+
0,
0-
0.
0/
00
01
b00000000000000000000000000000000 2
b00000000000000000000000000000000 3
b00000000000000000000000000000000 4
15
06
b00000000000000000000000000000000 7
b00000000000000000000000000000000 8
b00000000000000000000000000000000 9
b00000000000000000000000000000000 :
b00000000000000000000000000000000 ;
#5000
1#
1-
#10000
0#
0-
#15000
1#
1-
#20000
0#
1$
0-
1.
#25000
1#
1%
1'
b00000000000000000001000000000000 (
b00000000000000000000000010100101 )
1-
1/
11
b00000000000000000001000000000000 2
b00000000000000000000000010100101 3
#30000
0#
0-
#35000
1#
1&
1-
10
b00000000000000000001000000000000 ;
#40000
0#
0-
#45000
1#
0&
b00000000000000000001000000000100 (
b00000000000000000000000001010101 )
1-
00
b00000000000000000001000000000100 2
b00000000000000000000000001010101 3
b00000000000000000000000010100101 7
#50000
0#
0-
#55000
1#
1&
1-
10
b00000000000000000001000000000100 ;
#60000
0#
0-
#65000
1#
0&
0'
b00000000000000000001000000000000 (
1-
00
01
b00000000000000000001000000000000 2
b00000000000000000000000001010101 8
#70000
0#
0-
#75000
1#
1&
b00000000000000000000000010100101 *
1-
10
b00000000000000000000000010100101 4
b00000000000000000001000000000000 ;
#80000
0#
0-
#85000
1#
0&
b00000000000000000001000000000100 (
b00000000000000000000000000000000 *
1-
00
b00000000000000000001000000000100 2
b00000000000000000000000000000000 4
#90000
0#
0-
#95000
1#
1&
b00000000000000000000000001010101 *
1-
10
b00000000000000000000000001010101 4
b00000000000000000001000000000100 ;
#100000
0#
0-
#105000
1#
0%
0&
b00000000000000000000000000000000 *
1-
0/
00
b00000000000000000000000000000000 4
